rtl/Parameters.v
//=====================================================================
//
// Designer: Yuyang Chen
// Student number: 3220101054
//
// Description: To define all macro parameters in the project
//
// ====================================================================

//ISA relevant 
`define XLEN 64
`define ADDR_WIDTH 64
`define PC_BOOT_ADDR `ADDR_WIDTH'h0000_0000
`define PC_WIDTH 64

rtl/Std_sre_DFF.v
//=====================================================================
//
// Designer: Yuyang Chen
// Student number: 3220101054
//
// Description: Standardized DFF with synchronous reset and enable
//
// ====================================================================
`include "../rtl/Parameters.v"
module Std_sre_DFF#(
    parameter DATA_WIDTH = 64,
    parameter RESET_MODE = 1
)(
    input clk,
    input rst,
    input en,

    input [DATA_WIDTH-1:0] d,
    output reg [DATA_WIDTH-1:0] q
);
wire [DATA_WIDTH-1:0] reset_value_w; 
assign reset_value_w = RESET_MODE ? 0 : `PC_BOOT_ADDR;
always @(posedge clk)
begin
    if(!rst)
      q<= reset_value_w;
    else if(en)
      q<=d;
end
endmodule

rtl/Instr_Queue.v
//=====================================================================
//
// Designer: Yuyang Chen
// Student number: 3220101054
//
// Description: Instruction Fetch Unit
//
// ====================================================================
`include "../rtl/Parameters.v"
`include "../rtl/Std_sre_DFF.v"

module Instr_Queue (
    // Clock and Reset
    input  wire                   clk,                      // Clock signal, rising edge triggered
    input  wire                   rst,                      // Synchronous reset, active low (0: reset, 1: normal operation)

    // Inputs from IFU (Instruction Fetch Unit)
    input  wire  [`XLEN/2-1:0]     inst0_i,                  // First 32-bit instruction from IFU (part of a 64-bit instruction pair)
    input  wire  [`XLEN/2-1:0]     inst1_i,                  // Second 32-bit instruction from IFU (part of a 64-bit instruction pair)
    input  wire                   inst_valid_i,             // Indicates if the input instructions are valid (1: valid, 0: invalid)
    input  wire                   misaligned_exception_i,   // Indicates if the fetched instructions have a misaligned address exception (1: exception, 0: normal)
    input  wire  [`ADDR_WIDTH-1:0] misaligned_addr_i,        // Misaligned address from IFU, used for exception handling (64-bit address)
    input  wire                   ifu_flush_i,              // Flush signal from IFU or control unit, clears the queue (1: flush, 0: normal operation)

    // Input from Decode Stage
    input  wire                   decode_ready_i,           // Indicates if the Decode stage is ready to accept instructions (1: ready, 0: not ready)

    // Output to IFU
    output wire                   instr_queue_ready_o,        // Indicates if the queue is ready to accept new instructions from IFU (1: ready, 0: full)
                                                            // Used by IFU to determine whether to fetch and send new instructions

    // Outputs to Decode Stage
    output wire  [`XLEN/2-1:0]     inst0_o,                  // First 32-bit instruction output to Decode stage
    output wire  [`XLEN/2-1:0]     inst1_o,                  // Second 32-bit instruction output to Decode stage
    output wire                   inst_valid_o,             // Indicates if the output instructions are valid (1: valid, 0: invalid)
    output wire                   misaligned_exception_o,   // Misaligned exception indicator for the output instructions (1: exception, 0: normal)

    // Outputs for Exception Handling (Bypass Path)
    output wire                   misaligned_addr_valid_o,  // Indicates if the misaligned address output is valid (1: valid, 0: invalid)
    output wire  [`ADDR_WIDTH-1:0] misaligned_addr_bypass_o  // Misaligned address bypass output for exception handling (64-bit address)
);
localparam ENTRY_WIDTH = (`XLEN/2) + (`XLEN/2) + 1 + 1;

wire [ENTRY_WIDTH-1:0] queue_w [0:7];
wire [2:0] queue_write_ptr_w;
wire [2:0] queue_read_ptr_w;
wire queue_full_w;
wire queue_empty_w;
wire [2:0] next_queue_write_ptr_w;
wire [2:0] next_queue_read_ptr_w;
wire [ENTRY_WIDTH-1:0] queue_write_data_w;
wire [7:0] queue_write_en_w;
wire [`XLEN/2-1:0] next_inst0_o_w;
wire [`XLEN/2-1:0] next_inst1_o_w;
wire next_inst_valid_o_w;
wire next_misaligned_exception_o_w;
wire [`ADDR_WIDTH-1:0] misaligned_addr_reg_w;
wire misaligned_addr_reg_en_w;

    // Compute queue_full_w and queue_empty_w
assign queue_full_w = ((queue_write_ptr_w + 3'd1) == queue_read_ptr_w);
assign queue_empty_w = (queue_write_ptr_w == queue_read_ptr_w);
assign instr_queue_ready_o = ~queue_full_w;

    // Simplify queue_write_en_w generation
wire write_enable_condition;
assign write_enable_condition = inst_valid_i && ~queue_full_w;

assign queue_write_data_w = {inst0_i, inst1_i, inst_valid_i, misaligned_exception_i};

assign queue_write_en_w[0] = (write_enable_condition && (queue_write_ptr_w == 3'd0));
assign queue_write_en_w[1] = (write_enable_condition && (queue_write_ptr_w == 3'd1));
assign queue_write_en_w[2] = (write_enable_condition && (queue_write_ptr_w == 3'd2));
assign queue_write_en_w[3] = (write_enable_condition && (queue_write_ptr_w == 3'd3));
assign queue_write_en_w[4] = (write_enable_condition && (queue_write_ptr_w == 3'd4));
assign queue_write_en_w[5] = (write_enable_condition && (queue_write_ptr_w == 3'd5));
assign queue_write_en_w[6] = (write_enable_condition && (queue_write_ptr_w == 3'd6));
assign queue_write_en_w[7] = (write_enable_condition && (queue_write_ptr_w == 3'd7));

assign next_queue_write_ptr_w = ifu_flush_i ? queue_read_ptr_w :
                                   (write_enable_condition) ? (queue_write_ptr_w + 3'd1) : queue_write_ptr_w;

    genvar i;
    generate
        for (i = 0; i < 8; i = i + 1) begin : queue_dff
            Std_sre_DFF #(
                .DATA_WIDTH(ENTRY_WIDTH),
                .RESET_MODE(1)
            ) u_Std_sre_DFF_queue_entry (
                .clk(clk),
                .rst(rst),
                .en(queue_write_en_w[i]),
                .d(queue_write_data_w),
                .q(queue_w[i])
            );
        end
    endgenerate

    Std_sre_DFF #(
        .DATA_WIDTH(3),
        .RESET_MODE(1)
    ) u_Std_sre_DFF_queue_write_ptr (
        .clk(clk),
        .rst(rst),
        .en(1'b1),
        .d(next_queue_write_ptr_w),
        .q(queue_write_ptr_w)
    );

assign next_queue_read_ptr_w = ifu_flush_i ? queue_read_ptr_w :
                                  (~queue_empty_w && decode_ready_i) ? (queue_read_ptr_w + 3'd1) : queue_read_ptr_w;

wire [ENTRY_WIDTH-1:0] queue_read_data_w;
assign queue_read_data_w = (queue_read_ptr_w == 3'd0) ? queue_w[0] :
                               (queue_read_ptr_w == 3'd1) ? queue_w[1] :
                               (queue_read_ptr_w == 3'd2) ? queue_w[2] :
                               (queue_read_ptr_w == 3'd3) ? queue_w[3] :
                               (queue_read_ptr_w == 3'd4) ? queue_w[4] :
                               (queue_read_ptr_w == 3'd5) ? queue_w[5] :
                               (queue_read_ptr_w == 3'd6) ? queue_w[6] :
                               (queue_read_ptr_w == 3'd7) ? queue_w[7] : {ENTRY_WIDTH{1'b0}};

wire [`XLEN/2-1:0] queue_inst0_w = queue_read_data_w[ENTRY_WIDTH-1 -: `XLEN/2];
wire [`XLEN/2-1:0] queue_inst1_w = queue_read_data_w[ENTRY_WIDTH-`XLEN/2-1 -: `XLEN/2];
wire queue_inst_valid_w = queue_read_data_w[ENTRY_WIDTH-`XLEN-1];
wire queue_misaligned_exception_w = queue_read_data_w[ENTRY_WIDTH-`XLEN-2];

assign next_inst0_o_w = (~queue_empty_w && decode_ready_i) ? queue_inst0_w : {`XLEN/2{1'b0}};
assign next_inst1_o_w = (~queue_empty_w && decode_ready_i) ? queue_inst1_w : {`XLEN/2{1'b0}};
assign next_inst_valid_o_w = ifu_flush_i ? 1'b0 :
                                (~queue_empty_w && decode_ready_i) ? queue_inst_valid_w : 1'b0;
assign next_misaligned_exception_o_w = (~queue_empty_w && decode_ready_i) ? queue_misaligned_exception_w : 1'b0;

assign misaligned_addr_reg_en_w = inst_valid_i && misaligned_exception_i && ~queue_full_w;

    Std_sre_DFF #(
        .DATA_WIDTH(`ADDR_WIDTH)
    ) u_Std_sre_DFF_misaligned_addr_reg (
        .clk(clk),
        .rst(rst),
        .en(misaligned_addr_reg_en_w),
        .d(misaligned_addr_i),
        .q(misaligned_addr_reg_w)
    );

assign misaligned_addr_valid_o = misaligned_exception_o && inst_valid_o;
assign misaligned_addr_bypass_o = misaligned_addr_reg_w;

    Std_sre_DFF #(
        .DATA_WIDTH(3),
        .RESET_MODE(1)
    ) u_Std_sre_DFF_queue_read_ptr (
        .clk(clk),
        .rst(rst),
        .en(1'b1),
        .d(next_queue_read_ptr_w),
        .q(queue_read_ptr_w)
    );

    Std_sre_DFF #(
        .DATA_WIDTH(`XLEN/2),
        .RESET_MODE(1)
    ) u_Std_sre_DFF_inst0_o (
        .clk(clk),
        .rst(rst),
        .en(1'b1),
        .d(next_inst0_o_w),
        .q(inst0_o)
    );

    Std_sre_DFF #(
        .DATA_WIDTH(`XLEN/2),
        .RESET_MODE(1)
    ) u_Std_sre_DFF_inst1_o (
        .clk(clk),
        .rst(rst),
        .en(1'b1),
        .d(next_inst1_o_w),
        .q(inst1_o)
    );

    Std_sre_DFF #(
        .DATA_WIDTH(1),
        .RESET_MODE(1)
    ) u_Std_sre_DFF_inst_valid_o (
        .clk(clk),
        .rst(rst),
        .en(1'b1),
        .d(next_inst_valid_o_w),
        .q(inst_valid_o)
    );

    Std_sre_DFF #(
        .DATA_WIDTH(1),
        .RESET_MODE(1)
    ) u_Std_sre_DFF_misaligned_exception_o (
        .clk(clk),
        .rst(rst),
        .en(1'b1),
        .d(next_misaligned_exception_o_w),
        .q(misaligned_exception_o)
    );
endmodule

sim/Instr_Queue_tb.v
//=====================================================================
//
// Designer: Yuyang Chen
// Student number: 3220101054
//
// Description: IFU testbench
//
// ====================================================================

`timescale 1ns / 1ps
`include "../rtl/Instr_Queue.v"
`include "../rtl/Parameters.v"

module Instr_Queue_tb ();

// Declare integer variable
integer i;

// Parameters
localparam CLK_PERIOD = 10;  // Clock period in ns
localparam XLEN = 64;
localparam ADDR_WIDTH = 64;

// Inputs
reg                          clk;
reg                          rst;
reg       [XLEN/2-1:0]       inst0_i;
reg       [XLEN/2-1:0]       inst1_i;
reg                          inst_valid_i;
reg                          misaligned_exception_i;
reg       [ADDR_WIDTH-1:0]   misaligned_addr_i;
reg                          ifu_flush_i;
reg                          decode_ready_i;

// Outputs
wire                         instr_que_ready_o;
wire      [XLEN/2-1:0]       inst0_o;
wire      [XLEN/2-1:0]       inst1_o;
wire                         inst_valid_o;
wire                         misaligned_exception_o;
wire                         misaligned_addr_valid_o;
wire      [ADDR_WIDTH-1:0]   misaligned_addr_bypass_o;

// Instantiate the Unit Under Test (UUT)
Instr_Queue uut (
    .clk(clk),
    .rst(rst),
    .inst0_i(inst0_i),
    .inst1_i(inst1_i),
    .inst_valid_i(inst_valid_i),
    .misaligned_exception_i(misaligned_exception_i),
    .misaligned_addr_i(misaligned_addr_i),
    .ifu_flush_i(ifu_flush_i),
    .decode_ready_i(decode_ready_i),
    .instr_queue_ready_o(instr_que_ready_o),
    .inst0_o(inst0_o),
    .inst1_o(inst1_o),
    .inst_valid_o(inst_valid_o),
    .misaligned_exception_o(misaligned_exception_o),
    .misaligned_addr_valid_o(misaligned_addr_valid_o),
    .misaligned_addr_bypass_o(misaligned_addr_bypass_o)
);

// Clock generation
initial begin
    clk = 0;
    forever #(CLK_PERIOD/2) clk = ~clk;
end

// Test procedure
initial begin
    $dumpfile("Instr_Queue_tb.vcd");
    $dumpvars(0, Instr_Queue_tb);
    // Initialize inputs
    rst = 0;
    inst0_i = 0;
    inst1_i = 0;
    inst_valid_i = 0;
    misaligned_exception_i = 0;
    misaligned_addr_i = 0;
    ifu_flush_i = 0;
    decode_ready_i = 0;

    // Reset the system (synchronous reset)
    @(posedge clk);  // Wait for first clock edge (5ns)
    rst = 0;         // Assert reset
    repeat(2) @(posedge clk);  // Hold reset for 2 cycles (15ns)
    rst = 1;         // Deassert reset
    @(posedge clk);  // 25ns

    // Test Case 1: Normal Write and Read
    @(negedge clk);  // 30ns, just before 35ns rising edge
    $display("Test Case 1: Normal Write and Read");
    // Write two instructions
    inst0_i = 32'hDEADBEEF;
    inst1_i = 32'hCAFEBABE;
    inst_valid_i = 1;
    @(posedge clk);  // 35ns, signals should be sampled here

    @(negedge clk);  // 40ns, just before 45ns rising edge
    inst0_i = 32'h12345678;
    inst1_i = 32'h87654321;
    @(posedge clk);  // 45ns

    @(negedge clk);  // 50ns
    inst_valid_i = 0;  // Stop writing
    @(posedge clk);  // 55ns

    // Read instructions
    @(negedge clk);  // 60ns
    decode_ready_i = 1;
    @(posedge clk);  // 65ns
    repeat(2) @(posedge clk);  // 75ns, 85ns

    // Test Case 2: Fill Queue to Full
    @(negedge clk);  // 90ns
    $display("Test Case 2: Fill Queue to Full");
    inst_valid_i = 1;
    @(posedge clk);  // 95ns
    for (i = 0; i < 8; i = i + 1) begin
        @(negedge clk);  // 100ns, 110ns, ...
        inst0_i = 32'h00000000 + i;
        inst1_i = 32'h11111111 + i;
        @(posedge clk);  // 105ns, 115ns, ...
    end

    @(negedge clk);  // 170ns
    inst_valid_i = 0;
    @(posedge clk);  // 175ns

    @(negedge clk);  // 180ns
    inst_valid_i = 0;
    @(posedge clk);  // 185ns

    // Test Case 3: Misaligned Exception
    @(negedge clk);  // 190ns
    $display("Test Case 3: Misaligned Exception");
    decode_ready_i = 1;  // Clear queue
    @(posedge clk);  // 195ns
    repeat(8) @(posedge clk);  // 205ns ~ 275ns
    @(negedge clk);  // 280ns
    decode_ready_i = 0;
    @(posedge clk);  // 285ns

    // Write with misaligned exception
    @(negedge clk);  // 290ns
    inst0_i = 32'h55555555;
    inst1_i = 32'hAAAAAAAA;
    inst_valid_i = 1;
    misaligned_exception_i = 1;
    misaligned_addr_i = 64'hFFFF_FFFF_FFFF_FFFC;
    @(posedge clk);  // 295ns

    @(negedge clk);  // 300ns
    inst_valid_i = 0;
    misaligned_exception_i = 0;
    @(posedge clk);  // 305ns

    // Read with misaligned exception
    @(negedge clk);  // 310ns
    decode_ready_i = 1;
    @(posedge clk);  // 315ns
    @(negedge clk);  // 320ns
    decode_ready_i = 0;
    @(posedge clk);  // 325ns

    // Test Case 4: Flush Queue
    @(negedge clk);  // 330ns
    $display("Test Case 4: Flush Queue");
    // Write some instructions
    inst0_i = 32'hBBBBBBBB;
    inst1_i = 32'hCCCCCCCC;
    inst_valid_i = 1;
    @(posedge clk);  // 335ns
    @(posedge clk);  // 345ns

    @(negedge clk);  // 350ns
    inst_valid_i = 0;
    @(posedge clk);  // 355ns

    // Flush the queue
    @(negedge clk);  // 360ns
    ifu_flush_i = 1;
    @(posedge clk);  // 365ns
    @(negedge clk);  // 370ns
    ifu_flush_i = 0;
    @(posedge clk);  // 375ns

    // Read after flush
    @(negedge clk);  // 380ns
    decode_ready_i = 1;
    @(posedge clk);  // 385ns
    @(negedge clk);  // 390ns
    decode_ready_i = 0;
    @(posedge clk);  // 395ns

    // End simulation
    @(negedge clk);  // 400ns
    $display("Simulation Finished");
    $finish;
end

// Monitor outputs
initial begin
    $monitor("Time=%0t rst=%b inst_valid_i=%b decode_ready_i=%b instr_que_ready_o=%b inst_valid_o=%b inst0_o=%h inst1_o=%h misaligned_exception_o=%b misaligned_addr_bypass_o=%h",
             $time, rst, inst_valid_i, decode_ready_i, instr_que_ready_o, inst_valid_o, inst0_o, inst1_o, misaligned_exception_o, misaligned_addr_bypass_o);
end

// Debug signal changes
initial begin
    $monitor("Time=%0t Inputs: inst0_i=%h, inst1_i=%h, inst_valid_i=%b, misaligned_exception_i=%b",
             $time, inst0_i, inst1_i, inst_valid_i, misaligned_exception_i);
end

endmodule

sim/waves/Instr_Queue/Instr_Queue_tb.vcd
$date
	Fri Apr 25 22:37:57 2025
$end
$version
	Icarus Verilog
$end
$timescale
	1ps
$end
$scope module Instr_Queue_tb $end
$var wire 1 ! misaligned_exception_o $end
$var wire 1 " misaligned_addr_valid_o $end
$var wire 64 # misaligned_addr_bypass_o [63:0] $end
$var wire 1 $ instr_que_ready_o $end
$var wire 1 % inst_valid_o $end
$var wire 32 & inst1_o [31:0] $end
$var wire 32 ' inst0_o [31:0] $end
$var parameter 32 ( ADDR_WIDTH $end
$var parameter 32 ) CLK_PERIOD $end
$var parameter 32 * XLEN $end
$var reg 1 + clk $end
$var reg 1 , decode_ready_i $end
$var reg 1 - ifu_flush_i $end
$var reg 32 . inst0_i [31:0] $end
$var reg 32 / inst1_i [31:0] $end
$var reg 1 0 inst_valid_i $end
$var reg 64 1 misaligned_addr_i [63:0] $end
$var reg 1 2 misaligned_exception_i $end
$var reg 1 3 rst $end
$var integer 32 4 i [31:0] $end
$scope module uut $end
$var wire 1 + clk $end
$var wire 1 , decode_ready_i $end
$var wire 1 - ifu_flush_i $end
$var wire 32 5 inst0_i [31:0] $end
$var wire 32 6 inst1_i [31:0] $end
$var wire 1 0 inst_valid_i $end
$var wire 1 $ instr_queue_ready_o $end
$var wire 64 7 misaligned_addr_bypass_o [63:0] $end
$var wire 64 8 misaligned_addr_i [63:0] $end
$var wire 1 9 misaligned_addr_reg_en_w $end
$var wire 1 " misaligned_addr_valid_o $end
$var wire 1 2 misaligned_exception_i $end
$var wire 1 3 rst $end
$var wire 1 : write_enable_condition $end
$var wire 3 ; queue_write_ptr_w [2:0] $end
$var wire 8 < queue_write_en_w [7:0] $end
$var wire 66 = queue_write_data_w [65:0] $end
$var wire 3 > queue_read_ptr_w [2:0] $end
$var wire 66 ? queue_read_data_w [65:0] $end
$var wire 1 @ queue_misaligned_exception_w $end
$var wire 1 A queue_inst_valid_w $end
$var wire 32 B queue_inst1_w [31:0] $end
$var wire 32 C queue_inst0_w [31:0] $end
$var wire 1 D queue_full_w $end
$var wire 1 E queue_empty_w $end
$var wire 3 F next_queue_write_ptr_w [2:0] $end
$var wire 3 G next_queue_read_ptr_w [2:0] $end
$var wire 1 H next_misaligned_exception_o_w $end
$var wire 1 I next_inst_valid_o_w $end
$var wire 32 J next_inst1_o_w [31:0] $end
$var wire 32 K next_inst0_o_w [31:0] $end
$var wire 1 ! misaligned_exception_o $end
$var wire 64 L misaligned_addr_reg_w [63:0] $end
$var wire 1 % inst_valid_o $end
$var wire 32 M inst1_o [31:0] $end
$var wire 32 N inst0_o [31:0] $end
$var parameter 35 O ENTRY_WIDTH $end
$scope begin queue_dff[0] $end
$var parameter 2 P i $end
$scope module u_Std_sre_DFF_queue_entry $end
$var wire 1 + clk $end
$var wire 66 Q d [65:0] $end
$var wire 1 R en $end
$var wire 66 S reset_value_w [65:0] $end
$var wire 1 3 rst $end
$var parameter 35 T DATA_WIDTH $end
$var parameter 32 U RESET_MODE $end
$var reg 66 V q [65:0] $end
$upscope $end
$upscope $end
$scope begin queue_dff[1] $end
$var parameter 2 W i $end
$scope module u_Std_sre_DFF_queue_entry $end
$var wire 1 + clk $end
$var wire 66 X d [65:0] $end
$var wire 1 Y en $end
$var wire 66 Z reset_value_w [65:0] $end
$var wire 1 3 rst $end
$var parameter 35 [ DATA_WIDTH $end
$var parameter 32 \ RESET_MODE $end
$var reg 66 ] q [65:0] $end
$upscope $end
$upscope $end
$scope begin queue_dff[2] $end
$var parameter 3 ^ i $end
$scope module u_Std_sre_DFF_queue_entry $end
$var wire 1 + clk $end
$var wire 66 _ d [65:0] $end
$var wire 1 ` en $end
$var wire 66 a reset_value_w [65:0] $end
$var wire 1 3 rst $end
$var parameter 35 b DATA_WIDTH $end
$var parameter 32 c RESET_MODE $end
$var reg 66 d q [65:0] $end
$upscope $end
$upscope $end
$scope begin queue_dff[3] $end
$var parameter 3 e i $end
$scope module u_Std_sre_DFF_queue_entry $end
$var wire 1 + clk $end
$var wire 66 f d [65:0] $end
$var wire 1 g en $end
$var wire 66 h reset_value_w [65:0] $end
$var wire 1 3 rst $end
$var parameter 35 i DATA_WIDTH $end
$var parameter 32 j RESET_MODE $end
$var reg 66 k q [65:0] $end
$upscope $end
$upscope $end
$scope begin queue_dff[4] $end
$var parameter 4 l i $end
$scope module u_Std_sre_DFF_queue_entry $end
$var wire 1 + clk $end
$var wire 66 m d [65:0] $end
$var wire 1 n en $end
$var wire 66 o reset_value_w [65:0] $end
$var wire 1 3 rst $end
$var parameter 35 p DATA_WIDTH $end
$var parameter 32 q RESET_MODE $end
$var reg 66 r q [65:0] $end
$upscope $end
$upscope $end
$scope begin queue_dff[5] $end
$var parameter 4 s i $end
$scope module u_Std_sre_DFF_queue_entry $end
$var wire 1 + clk $end
$var wire 66 t d [65:0] $end
$var wire 1 u en $end
$var wire 66 v reset_value_w [65:0] $end
$var wire 1 3 rst $end
$var parameter 35 w DATA_WIDTH $end
$var parameter 32 x RESET_MODE $end
$var reg 66 y q [65:0] $end
$upscope $end
$upscope $end
$scope begin queue_dff[6] $end
$var parameter 4 z i $end
$scope module u_Std_sre_DFF_queue_entry $end
$var wire 1 + clk $end
$var wire 66 { d [65:0] $end
$var wire 1 | en $end
$var wire 66 } reset_value_w [65:0] $end
$var wire 1 3 rst $end
$var parameter 35 ~ DATA_WIDTH $end
$var parameter 32 !" RESET_MODE $end
$var reg 66 "" q [65:0] $end
$upscope $end
$upscope $end
$scope begin queue_dff[7] $end
$var parameter 4 #" i $end
$scope module u_Std_sre_DFF_queue_entry $end
$var wire 1 + clk $end
$var wire 66 $" d [65:0] $end
$var wire 1 %" en $end
$var wire 66 &" reset_value_w [65:0] $end
$var wire 1 3 rst $end
$var parameter 35 '" DATA_WIDTH $end
$var parameter 32 (" RESET_MODE $end
$var reg 66 )" q [65:0] $end
$upscope $end
$upscope $end
$scope module u_Std_sre_DFF_inst0_o $end
$var wire 1 + clk $end
$var wire 32 *" d [31:0] $end
$var wire 1 +" en $end
$var wire 32 ," reset_value_w [31:0] $end
$var wire 1 3 rst $end
$var parameter 32 -" DATA_WIDTH $end
$var parameter 32 ." RESET_MODE $end
$var reg 32 /" q [31:0] $end
$upscope $end
$scope module u_Std_sre_DFF_inst1_o $end
$var wire 1 + clk $end
$var wire 32 0" d [31:0] $end
$var wire 1 1" en $end
$var wire 32 2" reset_value_w [31:0] $end
$var wire 1 3 rst $end
$var parameter 32 3" DATA_WIDTH $end
$var parameter 32 4" RESET_MODE $end
$var reg 32 5" q [31:0] $end
$upscope $end
$scope module u_Std_sre_DFF_inst_valid_o $end
$var wire 1 + clk $end
$var wire 1 I d $end
$var wire 1 6" en $end
$var wire 1 7" reset_value_w $end
$var wire 1 3 rst $end
$var parameter 32 8" DATA_WIDTH $end
$var parameter 32 9" RESET_MODE $end
$var reg 1 % q $end
$upscope $end
$scope module u_Std_sre_DFF_misaligned_addr_reg $end
$var wire 1 + clk $end
$var wire 64 :" d [63:0] $end
$var wire 1 9 en $end
$var wire 64 ;" reset_value_w [63:0] $end
$var wire 1 3 rst $end
$var parameter 32 <" DATA_WIDTH $end
$var parameter 32 =" RESET_MODE $end
$var reg 64 >" q [63:0] $end
$upscope $end
$scope module u_Std_sre_DFF_misaligned_exception_o $end
$var wire 1 + clk $end
$var wire 1 H d $end
$var wire 1 ?" en $end
$var wire 1 @" reset_value_w $end
$var wire 1 3 rst $end
$var parameter 32 A" DATA_WIDTH $end
$var parameter 32 B" RESET_MODE $end
$var reg 1 ! q $end
$upscope $end
$scope module u_Std_sre_DFF_queue_read_ptr $end
$var wire 1 + clk $end
$var wire 3 C" d [2:0] $end
$var wire 1 D" en $end
$var wire 3 E" reset_value_w [2:0] $end
$var wire 1 3 rst $end
$var parameter 32 F" DATA_WIDTH $end
$var parameter 32 G" RESET_MODE $end
$var reg 3 H" q [2:0] $end
$upscope $end
$scope module u_Std_sre_DFF_queue_write_ptr $end
$var wire 1 + clk $end
$var wire 3 I" d [2:0] $end
$var wire 1 J" en $end
$var wire 3 K" reset_value_w [2:0] $end
$var wire 1 3 rst $end
$var parameter 32 L" DATA_WIDTH $end
$var parameter 32 M" RESET_MODE $end
$var reg 3 N" q [2:0] $end
$upscope $end
$upscope $end
$upscope $end
$enddefinitions $end
$comment Show the parameter values. $end
$dumpall
b1 M"
b11 L"
b1 G"
b11 F"
b1 B"
b1 A"
b1 ="
b1000000 <"
b1 9"
b1 8"
b1 4"
b100000 3"
b1 ."
b100000 -"
b1 ("
b1000010 '"
b111 #"
b1 !"
b1000010 ~
b110 z
b1 x
b1000010 w
b101 s
b1 q
b1000010 p
b100 l
b1 j
b1000010 i
b11 e
b1 c
b1000010 b
b10 ^
b1 \
b1000010 [
b1 W
b1 U
b1000010 T
b0 P
b1000010 O
b1000000 *
b1010 )
b1000000 (
$end
#0
$dumpvars
bx N"
b0 K"
1J"
bx I"
bx H"
b0 E"
1D"
bx C"
0@"
1?"
bx >"
b0 ;"
b0 :"
07"
16"
bx 5"
b0 2"
11"
b0 0"
bx /"
b0 ,"
1+"
b0 *"
bx )"
b0 &"
0%"
b0 $"
bx ""
b0 }
0|
b0 {
bx y
b0 v
0u
b0 t
bx r
b0 o
0n
b0 m
bx k
b0 h
0g
b0 f
bx d
b0 a
0`
b0 _
bx ]
b0 Z
0Y
b0 X
bx V
b0 S
0R
b0 Q
bx N
bx M
bx L
b0 K
b0 J
0I
0H
bx G
bx F
xE
xD
bx C
bx B
xA
x@
bx ?
bx >
b0 =
b0 <
bx ;
0:
09
b0 8
bx 7
b0 6
b0 5
bx 4
03
02
b0 1
00
b0 /
b0 .
0-
0,
0+
bx '
bx &
x%
x$
bx #
x"
x!
$end
#5000
b0 F
b0 I"
b0 C
b0 B
0A
0@
b0 G
b0 C"
1$
b0 ?
0"
b0 V
b0 ]
b0 d
b0 k
b0 r
b0 y
b0 ""
b0 )"
1E
0D
b0 ;
b0 N"
b0 #
b0 7
b0 L
b0 >"
b0 >
b0 H"
b0 '
b0 N
b0 /"
b0 &
b0 M
b0 5"
0%
0!
1+
#10000
0+
#15000
1+
#20000
0+
#25000
13
1+
#30000
0+
#35000
1+
#40000
1R
b1 F
b1 I"
b1 <
1:
10
b11001010111111101011101010111110 /
b11001010111111101011101010111110 6
b110111101010110110111110111011111100101011111110101110101011111010 =
b110111101010110110111110111011111100101011111110101110101011111010 Q
b110111101010110110111110111011111100101011111110101110101011111010 X
b110111101010110110111110111011111100101011111110101110101011111010 _
b110111101010110110111110111011111100101011111110101110101011111010 f
b110111101010110110111110111011111100101011111110101110101011111010 m
b110111101010110110111110111011111100101011111110101110101011111010 t
b110111101010110110111110111011111100101011111110101110101011111010 {
b110111101010110110111110111011111100101011111110101110101011111010 $"
b11011110101011011011111011101111 .
b11011110101011011011111011101111 5
0+
#45000
b11011110101011011011111011101111 C
b11001010111111101011101010111110 B
1A
b10 F
b10 I"
1Y
0R
b110111101010110110111110111011111100101011111110101110101011111010 ?
b10 <
b110111101010110110111110111011111100101011111110101110101011111010 V
0E
b1 ;
b1 N"
1+
#50000
b10000111011001010100001100100001 /
b10000111011001010100001100100001 6
b100100011010001010110011110001000011101100101010000110010000110 =
b100100011010001010110011110001000011101100101010000110010000110 Q
b100100011010001010110011110001000011101100101010000110010000110 X
b100100011010001010110011110001000011101100101010000110010000110 _
b100100011010001010110011110001000011101100101010000110010000110 f
b100100011010001010110011110001000011101100101010000110010000110 m
b100100011010001010110011110001000011101100101010000110010000110 t
b100100011010001010110011110001000011101100101010000110010000110 {
b100100011010001010110011110001000011101100101010000110010000110 $"
b10010001101000101011001111000 .
b10010001101000101011001111000 5
0+
#55000
b11 F
b11 I"
1`
0Y
b100 <
b10 ;
b10 N"
b100100011010001010110011110001000011101100101010000110010000110 ]
1+
#60000
0`
b10 F
b10 I"
b0 <
0:
b100100011010001010110011110001000011101100101010000110010000100 =
b100100011010001010110011110001000011101100101010000110010000100 Q
b100100011010001010110011110001000011101100101010000110010000100 X
b100100011010001010110011110001000011101100101010000110010000100 _
b100100011010001010110011110001000011101100101010000110010000100 f
b100100011010001010110011110001000011101100101010000110010000100 m
b100100011010001010110011110001000011101100101010000110010000100 t
b100100011010001010110011110001000011101100101010000110010000100 {
b100100011010001010110011110001000011101100101010000110010000100 $"
00
0+
#65000
1+
#70000
b1 G
b1 C"
1I
b11011110101011011011111011101111 K
b11011110101011011011111011101111 *"
b11001010111111101011101010111110 J
b11001010111111101011101010111110 0"
1,
0+
#75000
1I
b10010001101000101011001111000 K
b10010001101000101011001111000 *"
b10000111011001010100001100100001 J
b10000111011001010100001100100001 0"
b10010001101000101011001111000 C
b10000111011001010100001100100001 B
1A
b10 G
b10 C"
b100100011010001010110011110001000011101100101010000110010000110 ?
1%
b11001010111111101011101010111110 &
b11001010111111101011101010111110 M
b11001010111111101011101010111110 5"
b11011110101011011011111011101111 '
b11011110101011011011111011101111 N
b11011110101011011011111011101111 /"
b1 >
b1 H"
1+
#80000
0+
#85000
0I
b0 C
b0 B
0A
b0 J
b0 0"
b0 K
b0 *"
b0 ?
b10 G
b10 C"
1E
b10 >
b10 H"
b10010001101000101011001111000 '
b10010001101000101011001111000 N
b10010001101000101011001111000 /"
b10000111011001010100001100100001 &
b10000111011001010100001100100001 M
b10000111011001010100001100100001 5"
1+
#90000
0+
#95000
0%
b0 &
b0 M
b0 5"
b0 '
b0 N
b0 /"
1+
#100000
1`
b11 F
b11 I"
b100 <
1:
b100100011010001010110011110001000011101100101010000110010000110 =
b100100011010001010110011110001000011101100101010000110010000110 Q
b100100011010001010110011110001000011101100101010000110010000110 X
b100100011010001010110011110001000011101100101010000110010000110 _
b100100011010001010110011110001000011101100101010000110010000110 f
b100100011010001010110011110001000011101100101010000110010000110 m
b100100011010001010110011110001000011101100101010000110010000110 t
b100100011010001010110011110001000011101100101010000110010000110 {
b100100011010001010110011110001000011101100101010000110010000110 $"
10
0+
#105000
1I
b10010001101000101011001111000 K
b10010001101000101011001111000 *"
b10000111011001010100001100100001 J
b10000111011001010100001100100001 0"
b10010001101000101011001111000 C
b10000111011001010100001100100001 B
1A
b11 G
b11 C"
b100100011010001010110011110001000011101100101010000110010000110 ?
b100 F
b100 I"
1g
0`
b1000 <
b100100011010001010110011110001000011101100101010000110010000110 d
0E
b11 ;
b11 N"
b0 4
1+
