rtl/Parameters.v
//=====================================================================
//
// Designer: Yuyang Chen
// Student number: 3220101054
//
// Description: To define all macro parameters in the project
//
// ====================================================================

//ISA relevant 
`define XLEN 64
`define ADDR_WIDTH 64
`define PC_BOOT_ADDR `ADDR_WIDTH'h0000_0000
`define PC_WIDTH 64

rtl/Std_sre_DFF.v
//=====================================================================
//
// Designer: Yuyang Chen
// Student number: 3220101054
//
// Description: Standardized DFF with synchronous reset and enable
//
// ====================================================================
`include "../rtl/Parameters.v"
module Std_sre_DFF#(
    parameter DATA_WIDTH = 64,
    parameter RESET_MODE = 1
)(
    input clk,
    input rst,
    input en,

    input [DATA_WIDTH-1:0] d,
    output reg [DATA_WIDTH-1:0] q
);
wire [DATA_WIDTH-1:0] reset_value_w; 
assign reset_value_w = RESET_MODE ? 0 : `PC_BOOT_ADDR;
always @(posedge clk)
begin
    if(!rst)
      q<= reset_value_w;
    else if(en)
      q<=d;
end
endmodule

rtl/Instr_Align.v
//=====================================================================
//
// Designer: Yuyang Chen
// Student number: 3220101054
//
// Description: Instruction Alignment module
//
// ====================================================================
`include "../rtl/Parameters.v"
module Instr_Align(
    // Inputs
    input [`PC_WIDTH-1:0]   pc_i,         // Program Counter from IFU
    input [`ADDR_WIDTH-1:0] bpu_addr_i,   // Branch predicted target address
    input                   bpu_taken_i,  // Branch prediction taken signal
    input [`ADDR_WIDTH-1:0] bru_addr_i,   // Corrected branch address (mispredict)
    input                   bru_miss_i,   // Branch misprediction signal

    // Outputs
    output wire                   misaligned_exception, // Exception signal for misaligned address
    output wire [`ADDR_WIDTH-1:0] misaligned_addr       // Address causing the exception
);

    // Check alignment (RV64G: instructions must be 4-byte aligned)
    wire pc_misaligned_w = (pc_i[1:0] != 2'b00) ? 1'b1 : 1'b0;
    wire bpu_misaligned_w = (bpu_addr_i[1:0] != 2'b00);
    wire bru_misaligned_w = (bru_addr_i[1:0] != 2'b00);

    // Generate exception if any address is misaligned
    // Priority: bru_mispredict > bp_predict_taken > pc
    assign misaligned_exception = bru_miss_i ? bru_misaligned_w :
                                  bpu_taken_i ? bpu_misaligned_w :
                                  pc_misaligned_w;

    // Output the address causing the exception
    assign misaligned_addr = bru_miss_i ? bru_addr_i :
                             bpu_taken_i ? bpu_addr_i :
                             pc_i;

endmodule

rtl/PipelineControl.v
//=====================================================================
//
// Designer: Yuyang Chen
// Student number: 3220101054
//
// Description: Control flush and stall for pipeline
//
// ====================================================================
`include "../rtl/Parameters.v"
module PipelineControl (
    input        icache_hit_i,
    input        icache_ready_i,
    input        instr_queue_ready_i,
    input        bru_miss_i,
    input        exception_flush_i,
    input        interrupt_stall_i,
    output wire  stall_o,
    output wire  flush_o
);
assign stall_o = !icache_hit_i || !icache_ready_i || !instr_queue_ready_i || interrupt_stall_i;
assign flush_o = bru_miss_i || exception_flush_i;

endmodule

rtl/IFU.v
//=====================================================================
//
// Designer: Yuyang Chen
// Student number: 3220101054
//
// Description: Instruction Fetch Unit
//
// ====================================================================
`include "../rtl/Parameters.v"
`include "../rtl/PipelineControl.v"
`include "../rtl/Std_sre_DFF.v"
`include "../rtl/Instr_Align.v"
module IFU(
    //system signals
    input                         clk,
    input                         rst,

    // From Branch Prediction Unit
    input                         bpu_taken_i,
    input       [`ADDR_WIDTH-1:0] bpu_addr_i,

    // Branch Mis-prediction Feedback (from BRU)
    input                         bru_miss_i,                  //mispredict
    input       [`ADDR_WIDTH-1:0] bru_addr_i,                  //corret addr

    // I-Cache Interface
    output wire [`ADDR_WIDTH-1:0] icache_addr_o,               // Address to I-Cache (PC)
    input                         icache_hit_i,                // I-Cache hit signal
    input       [`XLEN-1:0]       icache_data_i,               // Two instructions (8 bytes) from I-Cache
    input                         icache_valid_i,              // I-Cache data valid
    input                         icache_ready_i,//handshake   // I-Cache ready to accept new request

    // Instruction Queue Interface
    output wire [`XLEN/2-1:0]     inst0_o,                     // First instruction (4 bytes)
    output wire [`XLEN/2-1:0]     inst1_o,                     // Second instruction (4 bytes)
    output wire                   inst_valid_o,                // Instructions valid
    input                         instr_queue_ready_i,//handshake   // Instruction Queue ready to accept instructions
    output wire                   misaligned_exception_o, // Exception signal for misaligned address
    output wire [`ADDR_WIDTH-1:0] misaligned_addr_o,       // Address causing the exception  
    
    //
    input                         exception_flush_i,   // flush caused by exceptions
    input                         interrupt_stall_i,   //stall caused by interruption

    // Pipeline Control
    output wire                   ifu_stall_o,                    // Stall signal to pipeline
    output wire                   ifu_flush_o                    // Flush signal to pipeline


);
//pc generation
wire [`XLEN-1:0] current_pc_w;
wire [`XLEN-1:0] next_pc_w;
assign next_pc_w = bru_miss_i ? bru_addr_i :
                    bpu_taken_i ? bpu_addr_i :
                    current_pc_w + 8;  // If miss, addr; not miss --> if taken, addr; not taken, pc+8
//instantiation for PipelineControl
wire stall_w, flush_w;
wire en;
PipelineControl u_PipelineControl(
    .icache_hit_i(icache_hit_i),
    .icache_ready_i(icache_ready_i),
    .instr_queue_ready_i(instr_queue_ready_i),
    .bru_miss_i(bru_miss_i),
    .exception_flush_i(exception_flush_i),
    .interrupt_stall_i(interrupt_stall_i),
    .stall_o(stall_w),
    .flush_o(flush_w)
);
assign ifu_stall_o = stall_w;
assign ifu_flush_o = flush_w || misaligned_exception_w; // Flush if misaligned exception
assign en = !ifu_stall_o;

assign icache_addr_o = current_pc_w;
// Instruction outputs (directly from I-Cache)
wire [`XLEN/2-1:0] inst0_w, inst1_w;
wire inst_valid_w;
assign inst0_w = icache_data_i[`XLEN/2-1:0];  // First 4-byte instruction
assign inst1_w = icache_data_i[`XLEN-1:`XLEN/2]; // Second 4-byte instruction
assign inst_valid_w = icache_valid_i && !ifu_flush_o; // Valid only if I-Cache data is valid and no flush

// Instantiation of Standardized DFF for current PC
Std_sre_DFF #(
    .DATA_WIDTH(`PC_WIDTH),
    .RESET_MODE(0) // Reset mode: 0 = PC_BOOT_ADDR, 1 = 0
) u_Std_sre_DFF_pc (
    .clk(clk),
    .rst(rst),
    .en(en),
    .d(next_pc_w),
    .q(current_pc_w)
);
// Instantiation of Standardized DFF for instruction output
Std_sre_DFF #(
    .DATA_WIDTH(`XLEN/2),
    .RESET_MODE(1)
) u_Std_sre_DFF_inst0 (
    .clk(clk),
    .rst(rst),
    .en(en),
    .d(inst0_w),
    .q(inst0_o)
);
Std_sre_DFF #(
    .DATA_WIDTH(`XLEN/2),
    .RESET_MODE(1)
) u_Std_sre_DFF_inst1 (
    .clk(clk),
    .rst(rst),
    .en(en),
    .d(inst1_w),
    .q(inst1_o)
);
// Instantiation of Standardized DFF for instruction valid output
Std_sre_DFF #(
    .DATA_WIDTH(1),
    .RESET_MODE(1)
) u_Std_sre_DFF_inst_valid (
    .clk(clk),
    .rst(rst),
    .en(en),
    .d(inst_valid_w),
    .q(inst_valid_o)
);

wire misaligned_exception_w;
wire [`ADDR_WIDTH-1:0] misaligned_addr_w;
//instruction alignment
Instr_Align u_Instr_Align(
    .pc_i(current_pc_w),
    .bpu_addr_i(bpu_addr_i),
    .bpu_taken_i(bpu_taken_i),
    .bru_addr_i(bru_addr_i),
    .bru_miss_i(bru_miss_i),
    .misaligned_exception(misaligned_exception_w),
    .misaligned_addr(misaligned_addr_w)
);

//Instantation of Standardized DFF for misaligned exception
Std_sre_DFF #(
    .DATA_WIDTH(1),
    .RESET_MODE(1)
) u_Std_sre_DFF_misaligned_exception (
    .clk(clk),
    .rst(rst),
    .en(en),
    .d(misaligned_exception_w),
    .q(misaligned_exception_o)
);
//Instantation of Standardized DFF for misaligned address
Std_sre_DFF #(
    .DATA_WIDTH(`ADDR_WIDTH),
    .RESET_MODE(1)
) u_Std_sre_DFF_misaligned_addr (
    .clk(clk),
    .rst(rst),
    .en(en),
    .d(misaligned_addr_w),
    .q(misaligned_addr_o)
);
endmodule

sim/ifu_tb.v
//=====================================================================
//
// Designer: Yuyang Chen
// Student number: 3220101054
//
// Description: IFU testbench
//
// ====================================================================
/*
`include "Std_sre_DFF.v"
`include "PipelineControl.v"
`include "Instru_Align.v"
`include "IFU.v"
*/
`timescale 1ns / 1ps
`include "../rtl/IFU.v"
`include "../rtl/Parameters.v"

module ifu_tb;

    // Testbench signals
    reg clk;
    reg rst;
    reg bpu_taken_i;
    reg [`ADDR_WIDTH-1:0] bpu_addr_i;
    reg bru_miss_i;
    reg [`ADDR_WIDTH-1:0] bru_addr_i;
    reg icache_hit_i;
    reg [`XLEN-1:0] icache_data_i;
    reg icache_valid_i;
    reg icache_ready_i;
    reg iqueue_ready_i;
    reg exception_flush_i;
    reg interrupt_stall_i;

    wire [`ADDR_WIDTH-1:0] icache_addr_o;
    wire [`XLEN/2-1:0] inst0_o;
    wire [`XLEN/2-1:0] inst1_o;
    wire inst_valid_o;
    wire ifu_stall_o;
    wire ifu_flush_o;
    wire misaligned_exception_o;
    wire [`ADDR_WIDTH-1:0] misaligned_addr_o;

    // Instantiate IFU
    IFU u_IFU (
        .clk(clk),
        .rst(rst),
        .bpu_taken_i(bpu_taken_i),
        .bpu_addr_i(bpu_addr_i),
        .bru_miss_i(bru_miss_i),
        .bru_addr_i(bru_addr_i),
        .icache_addr_o(icache_addr_o),
        .icache_hit_i(icache_hit_i),
        .icache_data_i(icache_data_i),
        .icache_valid_i(icache_valid_i),
        .icache_ready_i(icache_ready_i),
        .inst0_o(inst0_o),
        .inst1_o(inst1_o),
        .inst_valid_o(inst_valid_o),
        .instr_queue_ready_i(iqueue_ready_i),
        .exception_flush_i(exception_flush_i),
        .interrupt_stall_i(interrupt_stall_i),
        .ifu_stall_o(ifu_stall_o),
        .ifu_flush_o(ifu_flush_o),
        .misaligned_exception_o(misaligned_exception_o),
        .misaligned_addr_o(misaligned_addr_o)
    );

    // I-Cache simulation
    reg [63:0] icache_mem [0:1023];  // Simulate 4KB I-Cache (1024 entries of 64-bit data)
    wire [9:0] icache_index;  // Index into icache_mem (10 bits for 1024 entries)
    assign icache_index = icache_addr_o[12:3];  // Map address to index (8-byte aligned)

    // Simulate I-Cache behavior
    always @(*) begin
        if (icache_hit_i && icache_ready_i && icache_valid_i) begin
            icache_data_i = icache_mem[icache_index];
        end else begin
            icache_data_i = 64'h0;
        end
    end

    // Clock generation
    initial begin
        clk = 0;
        forever #5 clk = ~clk;  // 10ns period
    end
integer i;
    // Initialize I-Cache with predefined instructions
    initial begin
        // Preload I-Cache with some RISC-V instructions
        // Address 0x0: addi x1, x0, 5 (0x00500093) | addi x2, x0, 10 (0x00A00113)
        icache_mem[0] = {32'h00A00113, 32'h00500093};
        // Address 0x8: beq x1, x2, 8 (0x00208463) | nop (0x00000013)
        icache_mem[1] = {32'h00000013, 32'h00208463};
        // Address 0x10: add x3, x1, x2 (0x002081B3) | sub x4, x1, x2 (0x40208233)
        icache_mem[2] = {32'h40208233, 32'h002081B3};
        // Address 0x1000: jal x1, 4 (0x004000EF) | nop (0x00000013)
        icache_mem[64'h200] = {32'h00000013, 32'h004000EF};
        // Address 0x2000: addi x5, x0, 15 (0x00F00293) | nop (0x00000013)
        icache_mem[1023] = {32'h00000013, 32'h00F00293};  // Use the last valid index
        // Fill remaining entries with nop
        for ( i = 3; i < 1023; i++) begin
            if (i != 'h200 && i != 'h400) begin
                icache_mem[i] = {32'h00000013, 32'h00000013};  // nop | nop
            end
        end
    end

    // Test stimulus
    initial begin
        // Initialize signals
        rst = 0;
        bpu_taken_i = 0;
        bpu_addr_i = 64'h0;
        bru_miss_i = 0;
        bru_addr_i = 64'h0;
        icache_hit_i = 0;
        icache_data_i = 64'h0;
        icache_valid_i = 0;
        icache_ready_i = 0;
        iqueue_ready_i = 0;
        exception_flush_i = 0;
        interrupt_stall_i = 0;

        // Dump signals to VCD file for GTKWave
        $dumpfile("ifu_tb.vcd");
        $dumpvars(0, ifu_tb);

        // Reset
        #10;
        rst = 1;
        $display("Test 1: Normal fetch with I-Cache hit");
        icache_hit_i = 1;
        icache_valid_i = 1;
        icache_ready_i = 1;
        iqueue_ready_i = 1;
        #10;
        if (icache_addr_o != 64'h8 || inst0_o != 32'h00500093 || inst1_o != 32'h00A00113 || inst_valid_o != 1) begin
            $display("Test 1 Failed: Normal fetch incorrect");
        end else begin
            $display("Test 1 Passed");
        end

        #10;  // PC increments to 0x10
        if (icache_addr_o != 64'h10 || inst0_o != 32'h00208463 || inst1_o != 32'h00000013 || inst_valid_o != 1) begin
            $display("Test 2 Failed: Normal fetch at 0x8 incorrect");
        end else begin
            $display("Test 2 Passed");
        end

        $display("Test 3: Branch prediction taken");
        bpu_taken_i = 1;
        bpu_addr_i = 64'h1000;
        #10;
        bpu_taken_i = 0;
        #10;
        if (icache_addr_o != 64'h1000 || inst0_o != 32'h004000EF || inst1_o != 32'h00000013) begin
            $display("Test 3 Failed: Branch prediction incorrect");
        end else begin
            $display("Test 3 Passed");
        end

        $display("Test 4: Branch misprediction");
        bru_miss_i = 1;
        bru_addr_i = 64'h2000;
        #10;
        bru_miss_i = 0;
        #10;
        if (icache_addr_o != 64'h2000 || inst0_o != 32'h00F00293 || inst1_o != 32'h00000013 || inst_valid_o != 0) begin
            $display("Test 4 Failed: Branch misprediction incorrect");
        end else begin
            $display("Test 4 Passed");
        end

        $display("Test 5: Misaligned PC");
        bpu_taken_i = 1;
        bpu_addr_i = 64'h1003;  // Not 4-byte aligned
        #10;
        bpu_taken_i = 0;
        #10;
        if (!misaligned_exception_o || misaligned_addr_o != 64'h1003 || !ifu_flush_o) begin
            $display("Test 5 Failed: Misaligned PC not detected");
        end else begin
            $display("Test 5 Passed");
        end

        $display("Test 6: I-Cache miss (stall)");
        icache_hit_i = 0;
        #10;
        if (!ifu_stall_o) begin
            $display("Test 6 Failed: I-Cache miss should stall");
        end else begin
            $display("Test 6 Passed");
        end
        icache_hit_i = 1;
        #10;

        $display("Test 7: Exception flush");
        exception_flush_i = 1;
        #10;
        exception_flush_i = 0;
        #10;
        if (inst_valid_o != 0 || !ifu_flush_o) begin
            $display("Test 7 Failed: Exception flush incorrect");
        end else begin
            $display("Test 7 Passed");
        end

        $display("Test 8: Interrupt stall");
        interrupt_stall_i = 1;
        #10;
        if (!ifu_stall_o) begin
            $display("Test 8 Failed: Interrupt stall incorrect");
        end else begin
            $display("Test 8 Passed");
        end
        interrupt_stall_i = 0;
        #10;

        // Finish simulation
        #100;
        $finish;
    end

endmodule

sim/waves/IFU/ifu_tb.vcd
$date
	Fri Apr 25 22:37:57 2025
$end
$version
	Icarus Verilog
$end
$timescale
	1ps
$end
$scope module ifu_tb $end
$var wire 1 ! misaligned_exception_o $end
$var wire 64 " misaligned_addr_o [63:0] $end
$var wire 1 # inst_valid_o $end
$var wire 32 $ inst1_o [31:0] $end
$var wire 32 % inst0_o [31:0] $end
$var wire 1 & ifu_stall_o $end
$var wire 1 ' ifu_flush_o $end
$var wire 10 ( icache_index [9:0] $end
$var wire 64 ) icache_addr_o [63:0] $end
$var reg 64 * bpu_addr_i [63:0] $end
$var reg 1 + bpu_taken_i $end
$var reg 64 , bru_addr_i [63:0] $end
$var reg 1 - bru_miss_i $end
$var reg 1 . clk $end
$var reg 1 / exception_flush_i $end
$var reg 64 0 icache_data_i [63:0] $end
$var reg 1 1 icache_hit_i $end
$var reg 1 2 icache_ready_i $end
$var reg 1 3 icache_valid_i $end
$var reg 1 4 interrupt_stall_i $end
$var reg 1 5 iqueue_ready_i $end
$var reg 1 6 rst $end
$var integer 32 7 i [31:0] $end
$scope module u_IFU $end
$var wire 64 8 bpu_addr_i [63:0] $end
$var wire 1 + bpu_taken_i $end
$var wire 64 9 bru_addr_i [63:0] $end
$var wire 1 - bru_miss_i $end
$var wire 1 . clk $end
$var wire 1 / exception_flush_i $end
$var wire 64 : icache_addr_o [63:0] $end
$var wire 64 ; icache_data_i [63:0] $end
$var wire 1 1 icache_hit_i $end
$var wire 1 2 icache_ready_i $end
$var wire 1 3 icache_valid_i $end
$var wire 1 ' ifu_flush_o $end
$var wire 1 & ifu_stall_o $end
$var wire 1 < inst_valid_w $end
$var wire 1 5 instr_queue_ready_i $end
$var wire 1 4 interrupt_stall_i $end
$var wire 1 6 rst $end
$var wire 1 = stall_w $end
$var wire 64 > next_pc_w [63:0] $end
$var wire 1 ? misaligned_exception_w $end
$var wire 1 ! misaligned_exception_o $end
$var wire 64 @ misaligned_addr_w [63:0] $end
$var wire 64 A misaligned_addr_o [63:0] $end
$var wire 1 # inst_valid_o $end
$var wire 32 B inst1_w [31:0] $end
$var wire 32 C inst1_o [31:0] $end
$var wire 32 D inst0_w [31:0] $end
$var wire 32 E inst0_o [31:0] $end
$var wire 1 F flush_w $end
$var wire 1 G en $end
$var wire 64 H current_pc_w [63:0] $end
$scope module u_Instr_Align $end
$var wire 64 I bpu_addr_i [63:0] $end
$var wire 1 + bpu_taken_i $end
$var wire 64 J bru_addr_i [63:0] $end
$var wire 1 - bru_miss_i $end
$var wire 1 K pc_misaligned_w $end
$var wire 64 L pc_i [63:0] $end
$var wire 1 ? misaligned_exception $end
$var wire 64 M misaligned_addr [63:0] $end
$var wire 1 N bru_misaligned_w $end
$var wire 1 O bpu_misaligned_w $end
$upscope $end
$scope module u_PipelineControl $end
$var wire 1 - bru_miss_i $end
$var wire 1 / exception_flush_i $end
$var wire 1 F flush_o $end
$var wire 1 1 icache_hit_i $end
$var wire 1 2 icache_ready_i $end
$var wire 1 5 instr_queue_ready_i $end
$var wire 1 4 interrupt_stall_i $end
$var wire 1 = stall_o $end
$upscope $end
$scope module u_Std_sre_DFF_inst0 $end
$var wire 1 . clk $end
$var wire 32 P d [31:0] $end
$var wire 1 G en $end
$var wire 32 Q reset_value_w [31:0] $end
$var wire 1 6 rst $end
$var parameter 32 R DATA_WIDTH $end
$var parameter 32 S RESET_MODE $end
$var reg 32 T q [31:0] $end
$upscope $end
$scope module u_Std_sre_DFF_inst1 $end
$var wire 1 . clk $end
$var wire 32 U d [31:0] $end
$var wire 1 G en $end
$var wire 32 V reset_value_w [31:0] $end
$var wire 1 6 rst $end
$var parameter 32 W DATA_WIDTH $end
$var parameter 32 X RESET_MODE $end
$var reg 32 Y q [31:0] $end
$upscope $end
$scope module u_Std_sre_DFF_inst_valid $end
$var wire 1 . clk $end
$var wire 1 < d $end
$var wire 1 G en $end
$var wire 1 Z reset_value_w $end
$var wire 1 6 rst $end
$var parameter 32 [ DATA_WIDTH $end
$var parameter 32 \ RESET_MODE $end
$var reg 1 # q $end
$upscope $end
$scope module u_Std_sre_DFF_misaligned_addr $end
$var wire 1 . clk $end
$var wire 64 ] d [63:0] $end
$var wire 1 G en $end
$var wire 64 ^ reset_value_w [63:0] $end
$var wire 1 6 rst $end
$var parameter 32 _ DATA_WIDTH $end
$var parameter 32 ` RESET_MODE $end
$var reg 64 a q [63:0] $end
$upscope $end
$scope module u_Std_sre_DFF_misaligned_exception $end
$var wire 1 . clk $end
$var wire 1 ? d $end
$var wire 1 G en $end
$var wire 1 b reset_value_w $end
$var wire 1 6 rst $end
$var parameter 32 c DATA_WIDTH $end
$var parameter 32 d RESET_MODE $end
$var reg 1 ! q $end
$upscope $end
$scope module u_Std_sre_DFF_pc $end
$var wire 1 . clk $end
$var wire 64 e d [63:0] $end
$var wire 1 G en $end
$var wire 64 f reset_value_w [63:0] $end
$var wire 1 6 rst $end
$var parameter 32 g DATA_WIDTH $end
$var parameter 32 h RESET_MODE $end
$var reg 64 i q [63:0] $end
$upscope $end
$upscope $end
$upscope $end
$enddefinitions $end
$comment Show the parameter values. $end
$dumpall
b0 h
b1000000 g
b1 d
b1 c
b1 `
b1000000 _
b1 \
b1 [
b1 X
b100000 W
b1 S
b100000 R
$end
#0
$dumpvars
bx i
b0 f
bx e
0b
bx a
b0 ^
bx ]
0Z
bx Y
b0 V
b0 U
bx T
b0 Q
b0 P
0O
0N
bx M
bx L
xK
b0 J
b0 I
bx H
0G
0F
bx E
b0 D
bx C
b0 B
bx A
bx @
x?
bx >
1=
0<
b0 ;
bx :
b0 9
b0 8
b1111111111 7
06
05
04
03
02
01
b0 0
0/
0.
0-
b0 ,
0+
b0 *
bx )
bx (
x'
1&
bx %
bx $
x#
bx "
x!
$end
#5000
0'
0?
b0 @
b0 M
b0 ]
0K
b1000 >
b1000 e
b0 (
b0 )
b0 :
b0 H
b0 L
b0 i
b0 %
b0 E
b0 T
b0 $
b0 C
b0 Y
0#
0!
b0 "
b0 A
b0 a
1.
#10000
1G
0&
0=
b10100000000000010010011 D
b10100000000000010010011 P
b101000000000000100010011 B
b101000000000000100010011 U
1<
b10100000000000010001001100000000010100000000000010010011 0
b10100000000000010001001100000000010100000000000010010011 ;
0.
15
12
13
11
16
#15000
b1000001000010001100011 D
b1000001000010001100011 P
b10011 B
b10011 U
b1000 @
b1000 M
b1000 ]
b10000 >
b10000 e
b1001100000000001000001000010001100011 0
b1001100000000001000001000010001100011 ;
b1 (
1#
b101000000000000100010011 $
b101000000000000100010011 C
b101000000000000100010011 Y
b10100000000000010010011 %
b10100000000000010010011 E
b10100000000000010010011 T
b1000 )
b1000 :
b1000 H
b1000 L
b1000 i
1.
#20000
0.
#25000
b1000001000000110110011 D
b1000001000000110110011 P
b1000000001000001000001000110011 B
b1000000001000001000001000110011 U
b10000 @
b10000 M
b10000 ]
b11000 >
b11000 e
b100000000100000100000100011001100000000001000001000000110110011 0
b100000000100000100000100011001100000000001000001000000110110011 ;
b10 (
b10000 )
b10000 :
b10000 H
b10000 L
b10000 i
b1000001000010001100011 %
b1000001000010001100011 E
b1000001000010001100011 T
b10011 $
b10011 C
b10011 Y
b1000 "
b1000 A
b1000 a
1.
#30000
b1000000000000 >
b1000000000000 e
b1000000000000 @
b1000000000000 M
b1000000000000 ]
0.
b1000000000000 *
b1000000000000 8
b1000000000000 I
1+
#35000
b10000000000000011101111 D
b10000000000000011101111 P
b10011 B
b10011 U
b1001100000000010000000000000011101111 0
b1001100000000010000000000000011101111 ;
b1000000000 (
b1000000000000 "
b1000000000000 A
b1000000000000 a
b1000000001000001000001000110011 $
b1000000001000001000001000110011 C
b1000000001000001000001000110011 Y
b1000001000000110110011 %
b1000001000000110110011 E
b1000001000000110110011 T
b1000000000000 )
b1000000000000 :
b1000000000000 H
b1000000000000 L
b1000000000000 i
1.
#40000
b1000000001000 >
b1000000001000 e
0.
0+
#45000
b10011 D
b10011 P
b1000000001000 @
b1000000001000 M
b1000000001000 ]
b1000000010000 >
b1000000010000 e
b1001100000000000000000000000000010011 0
b1001100000000000000000000000000010011 ;
b1000000001 (
b1000000001000 )
b1000000001000 :
b1000000001000 H
b1000000001000 L
b1000000001000 i
b10000000000000011101111 %
b10000000000000011101111 E
b10000000000000011101111 T
b10011 $
b10011 C
b10011 Y
1.
#50000
0<
1'
b10000000000000 >
b10000000000000 e
b10000000000000 @
b10000000000000 M
b10000000000000 ]
1F
0.
b10000000000000 ,
b10000000000000 9
b10000000000000 J
1-
#55000
b10100000000000010010011 D
b10100000000000010010011 P
b101000000000000100010011 B
b101000000000000100010011 U
b10100000000000010001001100000000010100000000000010010011 0
b10100000000000010001001100000000010100000000000010010011 ;
b0 (
b10000000000000 "
b10000000000000 A
b10000000000000 a
0#
b10011 %
b10011 E
b10011 T
b10000000000000 )
b10000000000000 :
b10000000000000 H
b10000000000000 L
b10000000000000 i
1.
#60000
1<
0'
b10000000001000 >
b10000000001000 e
0F
0.
0-
#65000
b1000001000010001100011 D
b1000001000010001100011 P
b10011 B
b10011 U
b10000000001000 @
b10000000001000 M
b10000000001000 ]
b10000000010000 >
b10000000010000 e
b1001100000000001000001000010001100011 0
b1001100000000001000001000010001100011 ;
b1 (
b10000000001000 )
b10000000001000 :
b10000000001000 H
b10000000001000 L
b10000000001000 i
b10100000000000010010011 %
b10100000000000010010011 E
b10100000000000010010011 T
b101000000000000100010011 $
b101000000000000100010011 C
b101000000000000100010011 Y
1#
1.
#70000
0<
1'
1?
b1000000000011 >
b1000000000011 e
b1000000000011 @
b1000000000011 M
b1000000000011 ]
1O
0.
b1000000000011 *
b1000000000011 8
b1000000000011 I
1+
#75000
b10000000000000011101111 D
b10000000000000011101111 P
1K
b1001100000000010000000000000011101111 0
b1001100000000010000000000000011101111 ;
b1000000000 (
b1000000000011 "
b1000000000011 A
b1000000000011 a
1!
0#
b10011 $
b10011 C
b10011 Y
b1000001000010001100011 %
b1000001000010001100011 E
b1000001000010001100011 T
b1000000000011 )
b1000000000011 :
b1000000000011 H
b1000000000011 L
b1000000000011 i
1.
#80000
b1000000001011 >
b1000000001011 e
0.
0+
#85000
b10011 D
b10011 P
b1000000001011 @
b1000000001011 M
b1000000001011 ]
b1000000010011 >
b1000000010011 e
b1001100000000000000000000000000010011 0
b1001100000000000000000000000000010011 ;
b1000000001 (
b1000000001011 )
b1000000001011 :
b1000000001011 H
b1000000001011 L
b1000000001011 i
b10000000000000011101111 %
b10000000000000011101111 E
b10000000000000011101111 T
1.
#90000
0G
1&
1=
b0 D
b0 P
b0 B
b0 U
b0 0
b0 ;
0.
01
#95000
1.
#100000
1G
0&
0=
b10011 D
b10011 P
b10011 B
b10011 U
b1001100000000000000000000000000010011 0
b1001100000000000000000000000000010011 ;
0.
11
#105000
b1000000010011 @
b1000000010011 M
b1000000010011 ]
b1000000011011 >
b1000000011011 e
b1000000010 (
b1000000010011 )
b1000000010011 :
b1000000010011 H
b1000000010011 L
b1000000010011 i
b10011 %
b10011 E
b10011 T
b1000000001011 "
b1000000001011 A
b1000000001011 a
1.
#110000
1F
0.
1/
#115000
b1000000011011 @
b1000000011011 M
b1000000011011 ]
b1000000100011 >
b1000000100011 e
b1000000011 (
b1000000010011 "
b1000000010011 A
b1000000010011 a
b1000000011011 )
b1000000011011 :
b1000000011011 H
b1000000011011 L
b1000000011011 i
1.
#120000
0F
0.
0/
#125000
b1000000100011 @
b1000000100011 M
b1000000100011 ]
b1000000101011 >
b1000000101011 e
b1000000100 (
b1000000100011 )
b1000000100011 :
b1000000100011 H
b1000000100011 L
b1000000100011 i
b1000000011011 "
b1000000011011 A
b1000000011011 a
1.
#130000
0G
1&
1=
0.
14
#135000
1.
#140000
1G
0&
0=
0.
04
#145000
b1000000101011 @
b1000000101011 M
b1000000101011 ]
b1000000110011 >
b1000000110011 e
b1000000101 (
b1000000101011 )
b1000000101011 :
b1000000101011 H
b1000000101011 L
b1000000101011 i
b1000000100011 "
b1000000100011 A
b1000000100011 a
1.
#150000
0.
#155000
b1000000110011 @
b1000000110011 M
b1000000110011 ]
b1000000111011 >
b1000000111011 e
b1000000110 (
b1000000101011 "
b1000000101011 A
b1000000101011 a
b1000000110011 )
b1000000110011 :
b1000000110011 H
b1000000110011 L
b1000000110011 i
1.
#160000
0.
#165000
b1000000111011 @
b1000000111011 M
b1000000111011 ]
b1000001000011 >
b1000001000011 e
b1000000111 (
b1000000111011 )
b1000000111011 :
b1000000111011 H
b1000000111011 L
b1000000111011 i
b1000000110011 "
b1000000110011 A
b1000000110011 a
1.
#170000
0.
#175000
b1000001000011 @
b1000001000011 M
b1000001000011 ]
b1000001001011 >
b1000001001011 e
b1000001000 (
b1000000111011 "
b1000000111011 A
b1000000111011 a
b1000001000011 )
b1000001000011 :
b1000001000011 H
b1000001000011 L
b1000001000011 i
1.
#180000
0.
#185000
b1000001001011 @
b1000001001011 M
b1000001001011 ]
b1000001010011 >
b1000001010011 e
b1000001001 (
b1000001001011 )
b1000001001011 :
b1000001001011 H
b1000001001011 L
b1000001001011 i
b1000001000011 "
b1000001000011 A
b1000001000011 a
1.
#190000
0.
#195000
b1000001010011 @
b1000001010011 M
b1000001010011 ]
b1000001011011 >
b1000001011011 e
b1000001010 (
b1000001001011 "
b1000001001011 A
b1000001001011 a
b1000001010011 )
b1000001010011 :
b1000001010011 H
b1000001010011 L
b1000001010011 i
1.
#200000
0.
#205000
b1000001011011 @
b1000001011011 M
b1000001011011 ]
b1000001100011 >
b1000001100011 e
b1000001011 (
b1000001011011 )
b1000001011011 :
b1000001011011 H
b1000001011011 L
b1000001011011 i
b1000001010011 "
b1000001010011 A
b1000001010011 a
1.
#210000
0.
#215000
b1000001100011 @
b1000001100011 M
b1000001100011 ]
b1000001101011 >
b1000001101011 e
b1000001100 (
b1000001011011 "
b1000001011011 A
b1000001011011 a
b1000001100011 )
b1000001100011 :
b1000001100011 H
b1000001100011 L
b1000001100011 i
1.
#220000
0.
#225000
b1000001101011 @
b1000001101011 M
b1000001101011 ]
b1000001110011 >
b1000001110011 e
b1000001101 (
b1000001101011 )
b1000001101011 :
b1000001101011 H
b1000001101011 L
b1000001101011 i
b1000001100011 "
b1000001100011 A
b1000001100011 a
1.
#230000
0.
#235000
b1000001110011 @
b1000001110011 M
b1000001110011 ]
b1000001111011 >
b1000001111011 e
b1000001110 (
b1000001101011 "
b1000001101011 A
b1000001101011 a
b1000001110011 )
b1000001110011 :
b1000001110011 H
b1000001110011 L
b1000001110011 i
1.
#240000
0.
#245000
b1000001111011 @
b1000001111011 M
b1000001111011 ]
b1000010000011 >
b1000010000011 e
b1000001111 (
b1000001111011 )
b1000001111011 :
b1000001111011 H
b1000001111011 L
b1000001111011 i
b1000001110011 "
b1000001110011 A
b1000001110011 a
1.
